README.txt
setup.py
vsearch.py
mvsearch.egg-info/PKG-INFO
mvsearch.egg-info/SOURCES.txt
mvsearch.egg-info/dependency_links.txt
mvsearch.egg-info/top_level.txt