Metadata-Version: 1.0
Name: mvsearch
Version: 1.0
Summary: The Head First Python Search Tools
Home-page: UNKNOWN
Author: majie
Author-email: 1206765895@qq.com
License: UNKNOWN
Platform: UNKNOWN
